odoo/addons/account_liquidity_forecast/README.rst
odoo/addons/account_liquidity_forecast/__init__.py
odoo/addons/account_liquidity_forecast/__manifest__.py
odoo/addons/account_liquidity_forecast/menuitems.xml
odoo/addons/account_liquidity_forecast/reports.xml
odoo/addons/account_liquidity_forecast/i18n/account_liquidity_forecast.pot
odoo/addons/account_liquidity_forecast/i18n/it.po
odoo/addons/account_liquidity_forecast/models/__init__.py
odoo/addons/account_liquidity_forecast/models/account_account.py
odoo/addons/account_liquidity_forecast/models/account_liquidity_forecast_planning_group.py
odoo/addons/account_liquidity_forecast/models/account_liquidity_forecast_planning_item.py
odoo/addons/account_liquidity_forecast/models/ir_actions_report.py
odoo/addons/account_liquidity_forecast/readme/CONTRIBUTORS.rst
odoo/addons/account_liquidity_forecast/readme/DESCRIPTION.rst
odoo/addons/account_liquidity_forecast/report/__init__.py
odoo/addons/account_liquidity_forecast/report/liquidity_forecast.py
odoo/addons/account_liquidity_forecast/report/liquidity_forecast_xlsx.py
odoo/addons/account_liquidity_forecast/report/templates/layouts.xml
odoo/addons/account_liquidity_forecast/report/templates/liquidity_forecast.xml
odoo/addons/account_liquidity_forecast/security/ir.model.access.csv
odoo/addons/account_liquidity_forecast/security/security.xml
odoo/addons/account_liquidity_forecast/static/description/icon.png
odoo/addons/account_liquidity_forecast/static/description/index.html
odoo/addons/account_liquidity_forecast/static/src/css/report.css
odoo/addons/account_liquidity_forecast/static/src/js/report.esm.js
odoo/addons/account_liquidity_forecast/static/src/js/report_action.esm.js
odoo/addons/account_liquidity_forecast/tests/__init__.py
odoo/addons/account_liquidity_forecast/tests/test_liquidity_forecast.py
odoo/addons/account_liquidity_forecast/views/account_liquidity_forecast_planning_group_views.xml
odoo_addon_account_liquidity_forecast-16.0.1.0.0.16.dist-info/METADATA
odoo_addon_account_liquidity_forecast-16.0.1.0.0.16.dist-info/WHEEL
odoo_addon_account_liquidity_forecast-16.0.1.0.0.16.dist-info/top_level.txt
odoo_addon_account_liquidity_forecast-16.0.1.0.0.16.dist-info/RECORD
